dash_auth_plus/__init__.py
dash_auth_plus/_version.py
dash_auth_plus/auth.py
dash_auth_plus/basic_auth.py
dash_auth_plus/clerk_auth.py
dash_auth_plus/group_protection.py
dash_auth_plus/oidc_auth.py
dash_auth_plus/package-info.json
dash_auth_plus/public_routes.py
dash_auth_plus/DashAuthComponents/ClerkProvider.py
dash_auth_plus/DashAuthComponents/UserProfile.py
dash_auth_plus/DashAuthComponents/UserProfilePage.py
dash_auth_plus/DashAuthComponents/__init__.py
dash_auth_plus/DashAuthComponents/_imports_.py
dash_auth_plus/DashAuthComponents/dash_auth_plus.js
dash_auth_plus/DashAuthComponents/dash_auth_plus.js.LICENSE.txt
dash_auth_plus/DashAuthComponents/dash_auth_plus.js.map
dash_auth_plus/DashAuthComponents/metadata.json
dash_auth_plus/DashAuthComponents/package-info.json
dash_auth_plus/DashAuthComponents/proptypes.js
dash_auth_plus-0.0.1a5.dist-info/licenses/LICENSE
dash_auth_plus-0.0.1a5.dist-info/METADATA
dash_auth_plus-0.0.1a5.dist-info/WHEEL
dash_auth_plus-0.0.1a5.dist-info/top_level.txt
dash_auth_plus-0.0.1a5.dist-info/RECORD
