Metadata-Version: 2.4
Name: dash_auth_plus
Version: 0.0.1a5
Summary: Dash Authorization Package.
Home-page: https://github.com/BSd3v
Author: Bryan Schroeder
Author-email: bryan.ri.schroeder@gmail.com
License: MIT
Classifier: Development Status :: 5 - Production/Stable
Classifier: Environment :: Web Environment
Classifier: Framework :: Flask
Classifier: Intended Audience :: Developers
Classifier: Intended Audience :: Education
Classifier: Intended Audience :: Financial and Insurance Industry
Classifier: Intended Audience :: Healthcare Industry
Classifier: Intended Audience :: Manufacturing
Classifier: Intended Audience :: Science/Research
Classifier: License :: OSI Approved :: MIT License
Classifier: Programming Language :: Python
Classifier: Programming Language :: Python :: 3
Classifier: Programming Language :: Python :: 3.8
Classifier: Programming Language :: Python :: 3.9
Classifier: Programming Language :: Python :: 3.10
Classifier: Programming Language :: Python :: 3.11
Classifier: Programming Language :: Python :: 3.12
Classifier: Topic :: Database :: Front-Ends
Classifier: Topic :: Office/Business :: Financial :: Spreadsheet
Classifier: Topic :: Scientific/Engineering :: Visualization
Classifier: Topic :: Software Development :: Libraries :: Application Frameworks
Classifier: Topic :: Software Development :: Widget Sets
Requires-Python: >=3.8
License-File: LICENSE
Requires-Dist: dash>=1.1.1
Requires-Dist: flask
Requires-Dist: werkzeug
Requires-Dist: python-dotenv
Provides-Extra: oidc
Requires-Dist: authlib; extra == "oidc"
Provides-Extra: clerk
Requires-Dist: authlib; extra == "clerk"
Requires-Dist: clerk-sdk; extra == "clerk"
Requires-Dist: clerk-backend-api==3.0.1; extra == "clerk"
Provides-Extra: all
Requires-Dist: authlib; extra == "all"
Requires-Dist: clerk-sdk; extra == "all"
Requires-Dist: clerk-backend-api==3.0.1; extra == "all"
Dynamic: author
Dynamic: author-email
Dynamic: classifier
Dynamic: description
Dynamic: description-content-type
Dynamic: home-page
Dynamic: license
Dynamic: license-file
Dynamic: provides-extra
Dynamic: requires-dist
Dynamic: requires-python
Dynamic: summary
